{
  "metadata": {
    "project": "Morocco DevOps Monitor",
    "version": "2.0",
    "generated_at": "2026-04-08T15:13:15.988158",
    "location": "GitHub Actions Cloud",
    "student": "AUI Morocco - DevOps Learning"
  },
  "summary": {
    "total_websites": 6,
    "up": 6,
    "blocked": 0,
    "down": 0
  },
  "results": [
    {
      "name": "AUI Morocco",
      "url": "https://www.aui.ma",
      "status": "UP",
      "code": 200,
      "time": 5.23,
      "timestamp": "15:13:14",
      "size": 170582
    },
    {
      "name": "Hespress",
      "url": "https://www.hespress.com",
      "status": "UP",
      "code": 200,
      "time": 0.17,
      "timestamp": "15:13:14",
      "size": 281455
    },
    {
      "name": "Avito Morocco",
      "url": "https://www.avito.ma",
      "status": "UP",
      "code": 200,
      "time": 0.51,
      "timestamp": "15:13:15",
      "size": 272004
    },
    {
      "name": "Google",
      "url": "https://www.google.com",
      "status": "UP",
      "code": 200,
      "time": 0.24,
      "timestamp": "15:13:15",
      "size": 183641
    },
    {
      "name": "LinkedIn",
      "url": "https://www.linkedin.com",
      "status": "UP",
      "code": 200,
      "time": 0.27,
      "timestamp": "15:13:15",
      "size": 141656
    },
    {
      "name": "GitHub",
      "url": "https://github.com",
      "status": "UP",
      "code": 200,
      "time": 0.06,
      "timestamp": "15:13:15",
      "size": 563994
    }
  ]
}