{
  "metadata": {
    "project": "Morocco DevOps Monitor",
    "version": "2.0",
    "generated_at": "2026-03-21T15:43:17.280095",
    "location": "GitHub Actions Cloud",
    "student": "AUI Morocco - DevOps Learning"
  },
  "summary": {
    "total_websites": 6,
    "up": 6,
    "blocked": 0,
    "down": 0
  },
  "results": [
    {
      "name": "AUI Morocco",
      "url": "https://www.aui.ma",
      "status": "UP",
      "code": 200,
      "time": 1.54,
      "timestamp": "15:43:15",
      "size": 170836
    },
    {
      "name": "Hespress",
      "url": "https://www.hespress.com",
      "status": "UP",
      "code": 200,
      "time": 0.08,
      "timestamp": "15:43:15",
      "size": 279462
    },
    {
      "name": "Avito Morocco",
      "url": "https://www.avito.ma",
      "status": "UP",
      "code": 200,
      "time": 1.04,
      "timestamp": "15:43:16",
      "size": 272909
    },
    {
      "name": "Google",
      "url": "https://www.google.com",
      "status": "UP",
      "code": 200,
      "time": 0.16,
      "timestamp": "15:43:16",
      "size": 187810
    },
    {
      "name": "LinkedIn",
      "url": "https://www.linkedin.com",
      "status": "UP",
      "code": 200,
      "time": 0.28,
      "timestamp": "15:43:17",
      "size": 141532
    },
    {
      "name": "GitHub",
      "url": "https://github.com",
      "status": "UP",
      "code": 200,
      "time": 0.14,
      "timestamp": "15:43:17",
      "size": 568995
    }
  ]
}