{
  "metadata": {
    "project": "Morocco DevOps Monitor",
    "version": "2.0",
    "generated_at": "2026-03-24T01:42:50.073604",
    "location": "GitHub Actions Cloud",
    "student": "AUI Morocco - DevOps Learning"
  },
  "summary": {
    "total_websites": 6,
    "up": 6,
    "blocked": 0,
    "down": 0
  },
  "results": [
    {
      "name": "AUI Morocco",
      "url": "https://www.aui.ma",
      "status": "UP",
      "code": 200,
      "time": 1.31,
      "timestamp": "01:42:48",
      "size": 170836
    },
    {
      "name": "Hespress",
      "url": "https://www.hespress.com",
      "status": "UP",
      "code": 200,
      "time": 0.14,
      "timestamp": "01:42:48",
      "size": 277935
    },
    {
      "name": "Avito Morocco",
      "url": "https://www.avito.ma",
      "status": "UP",
      "code": 200,
      "time": 0.77,
      "timestamp": "01:42:49",
      "size": 272326
    },
    {
      "name": "Google",
      "url": "https://www.google.com",
      "status": "UP",
      "code": 200,
      "time": 0.15,
      "timestamp": "01:42:49",
      "size": 188051
    },
    {
      "name": "LinkedIn",
      "url": "https://www.linkedin.com",
      "status": "UP",
      "code": 200,
      "time": 0.25,
      "timestamp": "01:42:50",
      "size": 141434
    },
    {
      "name": "GitHub",
      "url": "https://github.com",
      "status": "UP",
      "code": 200,
      "time": 0.05,
      "timestamp": "01:42:50",
      "size": 568965
    }
  ]
}