{
  "metadata": {
    "project": "Morocco DevOps Monitor",
    "version": "2.0",
    "generated_at": "2026-06-19T19:18:51.591655",
    "location": "GitHub Actions Cloud",
    "student": "AUI Morocco - DevOps Learning"
  },
  "summary": {
    "total_websites": 6,
    "up": 6,
    "blocked": 0,
    "down": 0
  },
  "results": [
    {
      "name": "AUI Morocco",
      "url": "https://www.aui.ma",
      "status": "UP",
      "code": 200,
      "time": 1.13,
      "timestamp": "19:18:50",
      "size": 175268
    },
    {
      "name": "Hespress",
      "url": "https://www.hespress.com",
      "status": "UP",
      "code": 200,
      "time": 0.07,
      "timestamp": "19:18:50",
      "size": 287944
    },
    {
      "name": "Avito Morocco",
      "url": "https://www.avito.ma",
      "status": "UP",
      "code": 200,
      "time": 0.52,
      "timestamp": "19:18:51",
      "size": 275861
    },
    {
      "name": "Google",
      "url": "https://www.google.com",
      "status": "UP",
      "code": 200,
      "time": 0.1,
      "timestamp": "19:18:51",
      "size": 230684
    },
    {
      "name": "LinkedIn",
      "url": "https://www.linkedin.com",
      "status": "UP",
      "code": 200,
      "time": 0.2,
      "timestamp": "19:18:51",
      "size": 141785
    },
    {
      "name": "GitHub",
      "url": "https://github.com",
      "status": "UP",
      "code": 200,
      "time": 0.03,
      "timestamp": "19:18:51",
      "size": 563872
    }
  ]
}