{
  "metadata": {
    "project": "Morocco DevOps Monitor",
    "version": "2.0",
    "generated_at": "2026-03-23T20:54:19.515313",
    "location": "GitHub Actions Cloud",
    "student": "AUI Morocco - DevOps Learning"
  },
  "summary": {
    "total_websites": 6,
    "up": 6,
    "blocked": 0,
    "down": 0
  },
  "results": [
    {
      "name": "AUI Morocco",
      "url": "https://www.aui.ma",
      "status": "UP",
      "code": 200,
      "time": 2.09,
      "timestamp": "20:54:17",
      "size": 170836
    },
    {
      "name": "Hespress",
      "url": "https://www.hespress.com",
      "status": "UP",
      "code": 200,
      "time": 0.19,
      "timestamp": "20:54:18",
      "size": 279064
    },
    {
      "name": "Avito Morocco",
      "url": "https://www.avito.ma",
      "status": "UP",
      "code": 200,
      "time": 0.97,
      "timestamp": "20:54:18",
      "size": 272921
    },
    {
      "name": "Google",
      "url": "https://www.google.com",
      "status": "UP",
      "code": 200,
      "time": 0.16,
      "timestamp": "20:54:19",
      "size": 188035
    },
    {
      "name": "LinkedIn",
      "url": "https://www.linkedin.com",
      "status": "UP",
      "code": 200,
      "time": 0.21,
      "timestamp": "20:54:19",
      "size": 141508
    },
    {
      "name": "GitHub",
      "url": "https://github.com",
      "status": "UP",
      "code": 200,
      "time": 0.15,
      "timestamp": "20:54:19",
      "size": 568963
    }
  ]
}